[
null,
{"id":1,"animationId":41,"consumable":true,"damage":{"critical":false,"elementId":0,"formula":"0","type":0,"variance":20},"description":"恢复生命值100。","effects":[{"code":11,"dataId":0,"value1":0,"value2":100}],"hitType":0,"iconIndex":176,"itypeId":1,"name":"强身水","note":"","occasion":0,"price":100,"repeats":1,"scope":7,"speed":0,"successRate":100,"tpGain":10},
{"id":2,"animationId":41,"consumable":true,"damage":{"critical":false,"elementId":0,"formula":"0","type":0,"variance":20},"description":"恢复魔法值100。","effects":[{"code":12,"dataId":0,"value1":0,"value2":20}],"hitType":0,"iconIndex":208,"itypeId":1,"name":"魔法水","note":"","occasion":0,"price":100,"repeats":1,"scope":7,"speed":0,"successRate":100,"tpGain":10},
{"id":3,"animationId":45,"consumable":true,"damage":{"critical":false,"elementId":0,"formula":"0","type":0,"variance":20},"description":"去掉各种异常状态。","effects":[{"code":22,"dataId":4,"value1":1,"value2":0},{"code":22,"dataId":5,"value1":1,"value2":0},{"code":22,"dataId":6,"value1":1,"value2":0},{"code":22,"dataId":7,"value1":1,"value2":0},{"code":22,"dataId":8,"value1":1,"value2":0},{"code":22,"dataId":9,"value1":1,"value2":0},{"code":22,"dataId":10,"value1":1,"value2":0}],"hitType":0,"iconIndex":181,"itypeId":1,"name":"驱散草","note":"","occasion":0,"price":500,"repeats":1,"scope":7,"speed":0,"successRate":100,"tpGain":50},
{"id":4,"animationId":49,"consumable":true,"damage":{"critical":false,"elementId":0,"formula":"b.mhp / 2","type":3,"variance":20},"description":"复活药水，灵丹妙药！","effects":[{"code":22,"dataId":1,"value1":1,"value2":0},{"code":11,"dataId":0,"value1":1,"value2":0},{"code":12,"dataId":0,"value1":1,"value2":0}],"hitType":0,"iconIndex":178,"itypeId":1,"name":"兴奋剂","note":"","occasion":0,"price":1000,"repeats":1,"scope":9,"speed":0,"successRate":100,"tpGain":100},
{"id":5,"animationId":41,"consumable":true,"damage":{"critical":false,"elementId":0,"formula":"0","type":0,"variance":20},"description":"跑商商品。","effects":[{"code":11,"dataId":0,"value1":0,"value2":1000}],"hitType":0,"iconIndex":185,"itypeId":1,"name":"人参","note":"","occasion":0,"price":500,"repeats":1,"scope":7,"speed":0,"successRate":100,"tpGain":0},
{"id":6,"animationId":41,"consumable":true,"damage":{"critical":false,"elementId":0,"formula":"0","type":0,"variance":20},"description":"跑商商品。","effects":[{"code":12,"dataId":0,"value1":0,"value2":500}],"hitType":0,"iconIndex":292,"itypeId":1,"name":"鹿茸","note":"","occasion":0,"price":400,"repeats":1,"scope":7,"speed":0,"successRate":100,"tpGain":0},
{"id":7,"animationId":41,"consumable":true,"damage":{"critical":false,"elementId":0,"formula":"0","type":0,"variance":20},"description":"跑商商品。","effects":[{"code":31,"dataId":3,"value1":5,"value2":0}],"hitType":0,"iconIndex":199,"itypeId":1,"name":"貂皮","note":"","occasion":0,"price":300,"repeats":1,"scope":7,"speed":0,"successRate":100,"tpGain":0},
{"id":8,"animationId":41,"consumable":true,"damage":{"critical":false,"elementId":0,"formula":"0","type":0,"variance":20},"description":"跑商商品。","effects":[{"code":11,"dataId":0,"value1":0.5,"value2":0},{"code":12,"dataId":0,"value1":0.5,"value2":0}],"hitType":0,"iconIndex":261,"itypeId":1,"name":"松茸","note":"","occasion":0,"price":200,"repeats":1,"scope":7,"speed":0,"successRate":100,"tpGain":0},
{"id":9,"animationId":0,"consumable":true,"damage":{"critical":false,"elementId":0,"formula":"0","type":0,"variance":20},"description":"学习技能【双重攻击】。","effects":[{"code":43,"dataId":3,"value1":1,"value2":0}],"hitType":0,"iconIndex":76,"itypeId":2,"name":"双击符","note":"","occasion":2,"price":100000,"repeats":1,"scope":11,"speed":0,"successRate":100,"tpGain":0},
{"id":10,"animationId":0,"consumable":true,"damage":{"critical":false,"elementId":0,"formula":"0","type":0,"variance":20},"description":"学习技能【治愈】。","effects":[{"code":43,"dataId":8,"value1":1,"value2":0}],"hitType":0,"iconIndex":72,"itypeId":2,"name":"治愈术","note":"","occasion":2,"price":100000,"repeats":1,"scope":7,"speed":0,"successRate":100,"tpGain":0},
{"id":11,"animationId":0,"consumable":true,"damage":{"critical":false,"elementId":0,"formula":"0","type":0,"variance":20},"description":"学习技能【火焰术】。","effects":[{"code":43,"dataId":9,"value1":1,"value2":0}],"hitType":0,"iconIndex":64,"itypeId":2,"name":"火焰术","note":"","occasion":2,"price":100000,"repeats":1,"scope":1,"speed":0,"successRate":100,"tpGain":0},
{"id":12,"animationId":0,"consumable":true,"damage":{"critical":false,"elementId":0,"formula":"0","type":0,"variance":20},"description":"学习技能【火星术】。","effects":[{"code":43,"dataId":10,"value1":1,"value2":0}],"hitType":0,"iconIndex":66,"itypeId":2,"name":"火星术","note":"","occasion":2,"price":100000,"repeats":1,"scope":1,"speed":0,"successRate":100,"tpGain":0},
{"id":13,"animationId":59,"consumable":true,"damage":{"critical":false,"elementId":0,"formula":"0","type":0,"variance":20},"description":"使敌人中毒。","effects":[{"code":21,"dataId":4,"value1":1,"value2":0}],"hitType":0,"iconIndex":177,"itypeId":2,"name":"毒符","note":"","occasion":0,"price":100000,"repeats":1,"scope":1,"speed":0,"successRate":100,"tpGain":0},
{"id":14,"animationId":62,"consumable":true,"damage":{"critical":false,"elementId":0,"formula":"0","type":0,"variance":20},"description":"使敌人睡眠。","effects":[{"code":21,"dataId":10,"value1":1,"value2":0}],"hitType":0,"iconIndex":8,"itypeId":2,"name":"睡符","note":"","occasion":0,"price":100000,"repeats":1,"scope":1,"speed":0,"successRate":100,"tpGain":0},
{"id":15,"animationId":0,"consumable":true,"damage":{"critical":false,"elementId":0,"formula":"0","type":0,"variance":20},"description":"角色隐身2秒钟。","effects":[{"code":44,"dataId":4,"value1":1,"value2":0}],"hitType":0,"iconIndex":308,"itypeId":2,"name":"隐身符","note":"","occasion":0,"price":100000,"repeats":1,"scope":8,"speed":0,"successRate":100,"tpGain":0},
{"id":16,"animationId":0,"consumable":true,"damage":{"critical":false,"elementId":0,"formula":"0","type":0,"variance":20},"description":"单人一次等级+10。","effects":[{"code":44,"dataId":3,"value1":1,"value2":0}],"hitType":0,"iconIndex":75,"itypeId":2,"name":"升级符","note":"","occasion":2,"price":900000,"repeats":1,"scope":7,"speed":0,"successRate":100,"tpGain":0},
{"id":17,"animationId":119,"consumable":true,"damage":{"critical":false,"elementId":0,"formula":"0","type":0,"variance":20},"description":"召唤飞船。","effects":[{"code":44,"dataId":2,"value1":1,"value2":0}],"hitType":0,"iconIndex":69,"itypeId":2,"name":"飞船符","note":"","occasion":0,"price":900000,"repeats":1,"scope":11,"speed":0,"successRate":100,"tpGain":0},
{"id":18,"animationId":120,"consumable":true,"damage":{"critical":false,"elementId":0,"formula":"0","type":0,"variance":20},"description":"找桃花岛黄岛主参观私家花园。","effects":[],"hitType":0,"iconIndex":188,"itypeId":2,"name":"私家花园令牌","note":"","occasion":0,"price":0,"repeats":1,"scope":11,"speed":0,"successRate":100,"tpGain":0},
{"id":19,"animationId":117,"consumable":false,"damage":{"critical":false,"elementId":0,"formula":"0","type":0,"variance":20},"description":"进入仙界凭证。","effects":[],"hitType":0,"iconIndex":234,"itypeId":2,"name":"仙界令牌","note":"","occasion":0,"price":0,"repeats":1,"scope":11,"speed":0,"successRate":100,"tpGain":0},
{"id":20,"animationId":118,"consumable":false,"damage":{"critical":false,"elementId":0,"formula":"0","type":0,"variance":20},"description":"进入神域凭证。","effects":[],"hitType":0,"iconIndex":231,"itypeId":2,"name":"神域令牌","note":"","occasion":0,"price":0,"repeats":1,"scope":11,"speed":0,"successRate":100,"tpGain":0},
{"id":21,"animationId":120,"consumable":false,"damage":{"critical":false,"elementId":0,"formula":"0","type":0,"variance":20},"description":"打开仓库。","effects":[{"code":44,"dataId":5,"value1":1,"value2":0}],"hitType":0,"iconIndex":246,"itypeId":2,"name":"仓库钥匙","note":"","occasion":0,"price":0,"repeats":1,"scope":11,"speed":0,"successRate":100,"tpGain":0},
{"id":22,"animationId":120,"consumable":false,"damage":{"critical":false,"elementId":0,"formula":"0","type":0,"variance":20},"description":"增减组员。","effects":[{"code":44,"dataId":6,"value1":1,"value2":0}],"hitType":0,"iconIndex":249,"itypeId":2,"name":"组员令符","note":"","occasion":0,"price":0,"repeats":1,"scope":11,"speed":0,"successRate":100,"tpGain":0},
{"id":23,"animationId":120,"consumable":false,"damage":{"critical":false,"elementId":0,"formula":"0","type":0,"variance":20},"description":"执行随机任务，获得神秘奖励。","effects":[{"code":44,"dataId":7,"value1":1,"value2":0}],"hitType":0,"iconIndex":191,"itypeId":2,"name":"随机任务书","note":"","occasion":0,"price":0,"repeats":1,"scope":11,"speed":0,"successRate":100,"tpGain":0},
{"id":24,"animationId":0,"consumable":true,"damage":{"critical":false,"elementId":0,"formula":"0","type":0,"variance":20},"description":"","effects":[],"hitType":0,"iconIndex":0,"itypeId":1,"name":"","note":"","occasion":0,"price":0,"repeats":1,"scope":7,"speed":0,"successRate":100,"tpGain":0},
{"id":25,"animationId":0,"consumable":true,"damage":{"critical":false,"elementId":0,"formula":"0","type":0,"variance":20},"description":"","effects":[],"hitType":0,"iconIndex":0,"itypeId":1,"name":"","note":"","occasion":0,"price":0,"repeats":1,"scope":7,"speed":0,"successRate":100,"tpGain":0},
{"id":26,"animationId":0,"consumable":true,"damage":{"critical":false,"elementId":0,"formula":"0","type":0,"variance":20},"description":"","effects":[],"hitType":0,"iconIndex":0,"itypeId":1,"name":"","note":"","occasion":0,"price":0,"repeats":1,"scope":7,"speed":0,"successRate":100,"tpGain":0},
{"id":27,"animationId":0,"consumable":true,"damage":{"critical":false,"elementId":0,"formula":"0","type":0,"variance":20},"description":"","effects":[],"hitType":0,"iconIndex":0,"itypeId":1,"name":"","note":"","occasion":0,"price":0,"repeats":1,"scope":7,"speed":0,"successRate":100,"tpGain":0},
{"id":28,"animationId":0,"consumable":true,"damage":{"critical":false,"elementId":0,"formula":"0","type":0,"variance":20},"description":"","effects":[],"hitType":0,"iconIndex":0,"itypeId":1,"name":"","note":"","occasion":0,"price":0,"repeats":1,"scope":7,"speed":0,"successRate":100,"tpGain":0},
{"id":29,"animationId":0,"consumable":true,"damage":{"critical":false,"elementId":0,"formula":"0","type":0,"variance":20},"description":"","effects":[],"hitType":0,"iconIndex":0,"itypeId":1,"name":"","note":"","occasion":0,"price":0,"repeats":1,"scope":7,"speed":0,"successRate":100,"tpGain":0},
{"id":30,"animationId":0,"consumable":true,"damage":{"critical":false,"elementId":0,"formula":"0","type":0,"variance":20},"description":"","effects":[],"hitType":0,"iconIndex":0,"itypeId":1,"name":"","note":"","occasion":0,"price":0,"repeats":1,"scope":7,"speed":0,"successRate":100,"tpGain":0},
{"id":31,"animationId":0,"consumable":true,"damage":{"critical":false,"elementId":0,"formula":"0","type":0,"variance":20},"description":"","effects":[],"hitType":0,"iconIndex":0,"itypeId":1,"name":"","note":"","occasion":0,"price":0,"repeats":1,"scope":7,"speed":0,"successRate":100,"tpGain":0},
{"id":32,"animationId":0,"consumable":true,"damage":{"critical":false,"elementId":0,"formula":"0","type":0,"variance":20},"description":"","effects":[],"hitType":0,"iconIndex":0,"itypeId":1,"name":"","note":"","occasion":0,"price":0,"repeats":1,"scope":7,"speed":0,"successRate":100,"tpGain":0},
{"id":33,"animationId":0,"consumable":true,"damage":{"critical":false,"elementId":0,"formula":"0","type":0,"variance":20},"description":"","effects":[],"hitType":0,"iconIndex":0,"itypeId":1,"name":"","note":"","occasion":0,"price":0,"repeats":1,"scope":7,"speed":0,"successRate":100,"tpGain":0},
{"id":34,"animationId":0,"consumable":true,"damage":{"critical":false,"elementId":0,"formula":"0","type":0,"variance":20},"description":"","effects":[],"hitType":0,"iconIndex":0,"itypeId":1,"name":"","note":"","occasion":0,"price":0,"repeats":1,"scope":7,"speed":0,"successRate":100,"tpGain":0},
{"id":35,"animationId":0,"consumable":true,"damage":{"critical":false,"elementId":0,"formula":"0","type":0,"variance":20},"description":"","effects":[],"hitType":0,"iconIndex":0,"itypeId":1,"name":"","note":"","occasion":0,"price":0,"repeats":1,"scope":7,"speed":0,"successRate":100,"tpGain":0},
{"id":36,"animationId":0,"consumable":true,"damage":{"critical":false,"elementId":0,"formula":"0","type":0,"variance":20},"description":"","effects":[],"hitType":0,"iconIndex":0,"itypeId":1,"name":"","note":"","occasion":0,"price":0,"repeats":1,"scope":7,"speed":0,"successRate":100,"tpGain":0},
{"id":37,"animationId":0,"consumable":true,"damage":{"critical":false,"elementId":0,"formula":"0","type":0,"variance":20},"description":"","effects":[],"hitType":0,"iconIndex":0,"itypeId":1,"name":"","note":"","occasion":0,"price":0,"repeats":1,"scope":7,"speed":0,"successRate":100,"tpGain":0},
{"id":38,"animationId":0,"consumable":true,"damage":{"critical":false,"elementId":0,"formula":"0","type":0,"variance":20},"description":"","effects":[],"hitType":0,"iconIndex":0,"itypeId":1,"name":"","note":"","occasion":0,"price":0,"repeats":1,"scope":7,"speed":0,"successRate":100,"tpGain":0},
{"id":39,"animationId":0,"consumable":true,"damage":{"critical":false,"elementId":0,"formula":"0","type":0,"variance":20},"description":"","effects":[],"hitType":0,"iconIndex":0,"itypeId":1,"name":"","note":"","occasion":0,"price":0,"repeats":1,"scope":7,"speed":0,"successRate":100,"tpGain":0},
{"id":40,"animationId":0,"consumable":true,"damage":{"critical":false,"elementId":0,"formula":"0","type":0,"variance":20},"description":"","effects":[],"hitType":0,"iconIndex":0,"itypeId":1,"name":"","note":"","occasion":0,"price":0,"repeats":1,"scope":7,"speed":0,"successRate":100,"tpGain":0}
]